pycorpkit/__init__.py
pycorpkit/urls.py
pycorpkit/accountx/__init__.py
pycorpkit/accountx/urls.py
pycorpkit/accountx/filters/__init__.py
pycorpkit/accountx/filters/roles.py
pycorpkit/accountx/filters/user.py
pycorpkit/accountx/migrations/0001_initial.py
pycorpkit/accountx/migrations/0002_initial.py
pycorpkit/accountx/migrations/0003_user_user_email_idx.py
pycorpkit/accountx/migrations/__init__.py
pycorpkit/accountx/models/__init__.py
pycorpkit/accountx/models/invitation.py
pycorpkit/accountx/models/permission.py
pycorpkit/accountx/models/role.py
pycorpkit/accountx/models/signal.py
pycorpkit/accountx/models/user.py
pycorpkit/accountx/permissions/__init__.py
pycorpkit/accountx/permissions/enforce.py
pycorpkit/accountx/permissions/setup.py
pycorpkit/accountx/serializers/__init__.py
pycorpkit/accountx/serializers/invitation.py
pycorpkit/accountx/serializers/login.py
pycorpkit/accountx/serializers/roles.py
pycorpkit/accountx/serializers/signup.py
pycorpkit/accountx/serializers/token.py
pycorpkit/accountx/serializers/user.py
pycorpkit/accountx/templates/email/signup_confirm.html
pycorpkit/accountx/templates/email/signup_confirm.txt
pycorpkit/accountx/templates/email/user_invite.html
pycorpkit/accountx/templates/email/user_invite.txt
pycorpkit/accountx/templates/email/user_reset_password.html
pycorpkit/accountx/templates/email/user_reset_password.txt
pycorpkit/accountx/usecases/__init__.py
pycorpkit/accountx/usecases/change_password.py
pycorpkit/accountx/usecases/invitation.py
pycorpkit/accountx/usecases/login.py
pycorpkit/accountx/usecases/register.py
pycorpkit/accountx/views/__init__.py
pycorpkit/accountx/views/change_password.py
pycorpkit/accountx/views/invitation.py
pycorpkit/accountx/views/login.py
pycorpkit/accountx/views/register.py
pycorpkit/accountx/views/role.py
pycorpkit/accountx/views/token.py
pycorpkit/accountx/views/user.py
pycorpkit/common/__init__.py
pycorpkit/common/paginator.py
pycorpkit/common/urls.py
pycorpkit/common/filters/__init__.py
django_pycorpkit-1.0.4.dist-info/METADATA
django_pycorpkit-1.0.4.dist-info/WHEEL
django_pycorpkit-1.0.4.dist-info/licenses/AUTHORS.rst
django_pycorpkit-1.0.4.dist-info/licenses/LICENSE.txt
django_pycorpkit-1.0.4.dist-info/RECORD
